{"cameraMode":{"drawMode":0,"name":"Shaded","section":"Shading Mode"},"sceneLighting":true,"audioPlay":false,"sceneViewState":{"showFog":true,"showMaterialUpdate":false,"showSkybox":true,"showFlares":true,"showImageEffects":true,"showParticleSystems":true},"in2DMode":false,"pivot":{"x":1.8969690799713135,"y":0.2417926788330078,"z":-0.09695972502231598},"rotation":{"x":-0.23172031342983247,"y":0.6696450710296631,"z":-0.2329745888710022,"w":-0.6660394668579102},"size":8.4881010055542,"orthographic":false}